LICENSE.txt
MANIFEST.in
README.md
setup.py
sklearnkernels/KANN.py
sklearnkernels/KSVM.py
sklearnkernels/KernelUtilities.py
sklearnkernels/__init__.py
sklearnkernels.egg-info/PKG-INFO
sklearnkernels.egg-info/SOURCES.txt
sklearnkernels.egg-info/dependency_links.txt
sklearnkernels.egg-info/requires.txt
sklearnkernels.egg-info/top_level.txt