Metadata-Version: 1.1
Name: sklearnkernels
Version: 0.1.0
Summary: A random test lib
Home-page: https://github.com/magohector/sklearnkernels/tree/master/sklearnkernels
Author: Mora Hector
Author-email: hector.mora@gmail.com
License: GPL
Download-URL: https://github.com/magohector/sklearnkernels/archive/V0.1.0.tar.gz
Keywords: ANN,SVM,Kernels
Platform: UNKNOWN
Classifier: Programming Language :: Python
Classifier: Programming Language :: Python :: 2.7
Classifier: Programming Language :: Python :: 3.3
Classifier: Programming Language :: Python :: 3.4
Classifier: Programming Language :: Python :: 3.5
Classifier: Programming Language :: Python :: 3.6
Classifier: Programming Language :: Python :: 3.7
